omop/__init__.py
omop/models.py
omop/migrations/0001_initial.py
omop/migrations/0002_alter_caresite_options_alter_cdmsource_options_and_more.py
omop/migrations/0003_remove_caresite__previous_runs_and_more.py
omop/migrations/__init__.py
omop-0.2.1.dist-info/LICENSE
omop-0.2.1.dist-info/WHEEL
omop-0.2.1.dist-info/METADATA
omop-0.2.1.dist-info/RECORD
