Metadata-Version: 2.3
Name: omop
Version: 0.2.1
Summary: OMOP Common Data Model [`source <https://github.com/laminlabs/omop/blob/main/omop/models.py>`__].
Author-email: Lamin Labs <open-source@lamin.ai>
Requires-Dist: lamindb>=1.0.5
Requires-Dist: pre-commit ; extra == "dev"
Requires-Dist: nox ; extra == "dev"
Requires-Dist: pytest>=6.0 ; extra == "dev"
Requires-Dist: pytest-cov ; extra == "dev"
Requires-Dist: nbproject_test ; extra == "dev"
Project-URL: Home, https://github.com/laminlabs/omop
Provides-Extra: dev
